ai_address_lib/__init__.py
ai_address_lib/bert_layer.py
ai_address_lib/class_names_layer.py
ai_address_lib/create_model.py
ai_address_lib/model_loader.py
ai_address_lib/predictions.py
ai_address_lib/tokenizer_utils.py
ai_address_lib-0.4.1.dist-info/LICENCE
ai_address_lib-0.4.1.dist-info/METADATA
ai_address_lib-0.4.1.dist-info/WHEEL
ai_address_lib-0.4.1.dist-info/top_level.txt
ai_address_lib-0.4.1.dist-info/RECORD
