Metadata-Version: 2.1
Name: ai_address_lib
Version: 0.4.1
Summary: Library for address model predictions
Author: Vova
Author-email: vova.safoschin@gmail.com
Classifier: Programming Language :: Python :: 3
Classifier: License :: OSI Approved :: MIT License
Classifier: Operating System :: OS Independent
Requires-Python: >=3.10
License-File: LICENCE
Requires-Dist: tensorflow>=2.16.1
Requires-Dist: transformers>=4.44.2
Requires-Dist: numpy>=1.26.4
Requires-Dist: h5py>=3.11.0
Requires-Dist: scipy>=1.14.1
Requires-Dist: tf-keras
Requires-Dist: sentencepiece
Requires-Dist: scikit-learn
Requires-Dist: tqdm
Requires-Dist: pandas
